[{"name":"Platane","path":"Platanus.json","length":32,"key":"Platanus"},{"name":"Orme","path":"Ulmus.json","length":2,"key":"Ulmus"},{"name":"Orme de Sibérie","path":"Zelkova.json","length":4,"key":"Zelkova"},{"name":"Arbre aux quarante écus","path":"Ginkgo.json","length":8,"key":"Ginkgo"},{"name":"Magnolia","path":"Magnolia.json","length":3,"key":"Magnolia"},{"name":"Hêtre","path":"Fagus.json","length":12,"key":"Fagus"},{"name":"Noisetier de Byzance","path":"Corylus.json","length":6,"key":"Corylus"},{"name":"Bouleau","path":"Betula.json","length":1,"key":"Betula"},{"name":"Pin","path":"Pinus.json","length":4,"key":"Pinus"},{"name":"Pterocarya","path":"Pterocarya.json","length":7,"key":"Pterocarya"},{"name":"Robinier","path":"Robinia.json","length":1,"key":"Robinia"},{"name":"Chêne","path":"Quercus.json","length":11,"key":"Quercus"},{"name":"Savonnier","path":"Koelreuteria.json","length":1,"key":"Koelreuteria"},{"name":"Tulipier","path":"Liriodendron.json","length":4,"key":"Liriodendron"},{"name":"Chicot du Canada","path":"Gymnocladus.json","length":2,"key":"Gymnocladus"},{"name":"Sophora","path":"Sophora.json","length":2,"key":"Sophora"},{"name":"Cèdre","path":"Cedrus.json","length":8,"key":"Cedrus"},{"name":"Cedrele","path":"Toona.json","length":1,"key":"Toona"},{"name":"Tamaris","path":"Tamarix.json","length":1,"key":"Tamarix"},{"name":"Cyprès Chauve","path":"Taxodium.json","length":3,"key":"Taxodium"},{"name":"Metaséquoia","path":"Metasequoia.json","length":1,"key":"Metasequoia"},{"name":"Sequoia","path":"Sequoiadendron.json","length":5,"key":"Sequoiadendron"},{"name":"Plaqueminier","path":"Diospyros.json","length":6,"key":"Diospyros"},{"name":"Marronnier","path":"Aesculus.json","length":9,"key":"Aesculus"},{"name":"Mûrier","path":"Morus.json","length":2,"key":"Morus"},{"name":"Erable","path":"Acer.json","length":6,"key":"Acer"},{"name":"Arbre aux mouchoirs","path":"Davidia.json","length":1,"key":"Davidia"},{"name":"If","path":"Taxus.json","length":4,"key":"Taxus"},{"name":"Aulne","path":"Alnus.json","length":1,"key":"Alnus"},{"name":"Libocèdre","path":"Calocedrus.json","length":2,"key":"Calocedrus"},{"name":"Catalpa","path":"Catalpa.json","length":3,"key":"Catalpa"},{"name":"Oranger des Osages","path":"Maclura.json","length":1,"key":"Maclura"},{"name":"Sequoia","path":"Sequoia.json","length":2,"key":"Sequoia"},{"name":"Frêne","path":"Fraxinus.json","length":1,"key":"Fraxinus"},{"name":"Micocoulier","path":"Celtis.json","length":2,"key":"Celtis"},{"name":"Saule","path":"Salix.json","length":2,"key":"Salix"},{"name":"Cryptomeria","path":"Cryptomeria.json","length":1,"key":"Cryptomeria"},{"name":"Sterculier","path":"Firmiana.json","length":1,"key":"Firmiana"},{"name":"Noyer","path":"Juglans.json","length":1,"key":"Juglans"},{"name":"Lilas de Perse","path":"Melia.json","length":2,"key":"Melia"},{"name":"Figuier","path":"Ficus.json","length":2,"key":"Ficus"},{"name":"Grenadier","path":"Punica.json","length":1,"key":"Punica"},{"name":"Paulownia","path":"Paulownia.json","length":1,"key":"Paulownia"},{"name":"Arbre à Gutta-Percha","path":"Eucommia.json","length":2,"key":"Eucommia"},{"name":"Tilleul","path":"Tilia.json","length":1,"key":"Tilia"},{"name":"Amandier","path":"Prunus.json","length":1,"key":"Prunus"},{"name":"Pistachier","path":"Pistacia.json","length":1,"key":"Pistacia"},{"name":"Araucaria","path":"Araucaria.json","length":1,"key":"Araucaria"}]