[{"taille":{"h":2,"p":5},"nom":"Laurier sauce","info":{"genre":"Laurus","espece":"nobilis","stade_developpement":"Jeune (arbre)"},"id":"8b5924677d6aa72b5b573776b4d0d118ad61197a","geo":{"type":"Point","coordinates":[2.33884942452574,48.88926505343642]},"meta":{"arrondissement":"PARIS 18E ARRDT","adresse":"CIMETIERE ST VINCENT / AVENUE DE LA FONTAINE DU BUT / DIV 7"}},{"taille":{"h":5,"p":51},"nom":"Laurier sauce","info":{"genre":"Laurus","espece":"nobilis","stade_developpement":"Adulte"},"id":"fd37351376bc655efb6b160123b8bac2d7d9b1c9","geo":{"type":"Point","coordinates":[2.339821830559011,48.82213902291552]},"meta":{"arrondissement":"PARIS 14E ARRDT","adresse":"PARC MONTSOURIS / 28 BOULEVARD JOURDAN"}},{"taille":{"h":8,"p":75},"nom":"Laurier sauce","info":{"genre":"Laurus","espece":"nobilis","stade_developpement":"Adulte"},"id":"10497c4d75201fd68ea7710936092346ad5b698e","geo":{"type":"Point","coordinates":[2.286175555421158,48.86254678137876]},"meta":{"arrondissement":"PARIS 16E ARRDT","adresse":"CIMETIERE DE PASSY / DIV 9"}},{"taille":{"h":8,"p":50},"nom":"Laurier sauce","info":{"genre":"Laurus","espece":"nobilis","stade_developpement":"Jeune (arbre)Adulte"},"id":"014f63df070a795951df1319b25e4b6a0d89c1d8","geo":{"type":"Point","coordinates":[2.363101493988533,48.83117726946335]},"meta":{"arrondissement":"PARIS 13E ARRDT","adresse":"YEO THOMAS (5) MAT"}},{"taille":{"h":10,"p":80},"nom":"Laurier sauce","info":{"genre":"Laurus","espece":"nobilis","stade_developpement":"Adulte"},"id":"34591172f74970de384eec11be7fe156fc5d944c","geo":{"type":"Point","coordinates":[2.395039836625166,48.8513036682244]},"meta":{"arrondissement":"PARIS 11E ARRDT","adresse":"PHILIPPE AUGUSTE (30B)"}},{"taille":{"h":6,"p":50},"nom":"Laurier sauce","info":{"genre":"Laurus","espece":"nobilis"},"id":"b8da615ceaaf7fd534199039267ec334c93034c3","geo":{"type":"Point","coordinates":[2.39968221420568,48.907278298944185]},"meta":{"arrondissement":"SEINE-SAINT-DENIS","adresse":"CIMETIERE DE PANTIN / DIV 167"}},{"taille":{"h":7,"p":70},"nom":"Laurier sauce","info":{"genre":"Laurus","espece":"nobilis"},"id":"99af7bfb531a22da27daa8317478dd70e2524330","geo":{"type":"Point","coordinates":[2.423368350761433,48.90659377982975]},"meta":{"arrondissement":"SEINE-SAINT-DENIS","adresse":"CIMETIERE DE PANTIN / DIV 164"}},{"taille":{"h":8,"p":65},"nom":"Laurier sauce","info":{"genre":"Laurus","espece":"nobilis","stade_developpement":"Adulte"},"id":"2df0003fb49936bce06f7a9c390734ff20f17eae","geo":{"type":"Point","coordinates":[2.269904523958517,48.84508387531874]},"meta":{"arrondissement":"PARIS 16E ARRDT","adresse":"JARDIN DE L HOPITAL SAINTE PERINE / 41 RUE MIRABEAU"}},{"taille":{"h":9,"p":50},"nom":"Laurier sauce","info":{"genre":"Laurus","espece":"nobilis"},"id":"ec1b3ab0df03b106c4cd889d5ca1702cb824bf54","geo":{"type":"Point","coordinates":[2.401055127496373,48.90848415187247]},"meta":{"arrondissement":"SEINE-SAINT-DENIS","adresse":"CIMETIERE DE PANTIN / DIV 165"}},{"taille":{"h":8,"p":0},"nom":"Laurier sauce","info":{"genre":"Laurus","espece":"nobilis","stade_developpement":"Adulte"},"id":"9fcbe2af5d9f8f921aeea0ab60dc65c1b8d4280a","geo":{"type":"Point","coordinates":[2.309731479783971,48.87909475911393]},"meta":{"arrondissement":"PARIS 8E ARRDT","adresse":"PARC MONCEAU"}},{"taille":{"h":7,"p":100},"nom":"Laurier sauce","info":{"genre":"Laurus","espece":"nobilis","stade_developpement":"Adulte"},"id":"9bb3290b085df9d3e50cf19d1d6223f32b8ef40c","geo":{"type":"Point","coordinates":[2.353779616669533,48.82617731114034]},"meta":{"arrondissement":"PARIS 13E ARRDT","adresse":"CRECHE / 158 RUE DE TOLBIAC"}},{"taille":{"h":2,"p":25},"nom":"Laurier sauce","info":{"genre":"Laurus","espece":"nobilis","stade_developpement":"Jeune (arbre)"},"id":"0058defee860719c905303c8c5a99a95cb24c227","geo":{"type":"Point","coordinates":[2.291249803215773,48.86271715797959]},"meta":{"arrondissement":"PARIS 16E ARRDT","adresse":"JARDINS DU TROCADERO / 3 PLACE DE VARSOVIE"}},{"taille":{"h":4,"p":10},"nom":"Laurier sauce","info":{"genre":"Laurus","espece":"nobilis"},"id":"4628a9f0c95bc5c5bffc7ca51904f25fb6e7571c","geo":{"type":"Point","coordinates":[2.40541959052864,48.90443794884154]},"meta":{"arrondissement":"SEINE-SAINT-DENIS","adresse":"CIMETIERE DE PANTIN / DIV 38"}},{"taille":{"h":6,"p":35},"nom":"Laurier sauce","info":{"genre":"Laurus","espece":"nobilis"},"id":"bc24150096fd08138ff82debf7fc22180a6f1b10","geo":{"type":"Point","coordinates":[2.327842254900681,48.83856199609956]},"meta":{"arrondissement":"PARIS 14E ARRDT","adresse":"CIMETIERE DE MONTPARNASSE GRAND / DIV 13"}},{"taille":{"h":4,"p":40},"nom":"Laurier sauce","info":{"genre":"Laurus","espece":"nobilis","stade_developpement":"Jeune (arbre)Adulte"},"id":"a7cd64a25487e1a2848a65d9e30d15551a7e6bac","geo":{"type":"Point","coordinates":[2.387681843297818,48.851518624361304]},"meta":{"arrondissement":"PARIS 11E ARRDT","adresse":"ECOLE MATERNELLE / 5 CITE SOUZY"}},{"taille":{"h":0,"p":0},"nom":"Laurier sauce","info":{"genre":"Laurus","espece":"nobilis","stade_developpement":"Jeune (arbre)Adulte"},"id":"98f7de8b4380eedb41cfa2e069a7e017332f016d","geo":{"type":"Point","coordinates":[2.403582532462864,48.86057520599422]},"meta":{"arrondissement":"PARIS 20E ARRDT","adresse":"CIMETIERE DE CHARONNE / DIV F2"}},{"taille":{"h":4,"p":20},"nom":"Laurier sauce","info":{"genre":"Laurus","espece":"nobilis"},"id":"fe571ff9d2301e3d110e8273663108c8c8abb6cd","geo":{"type":"Point","coordinates":[2.316213541976853,48.868088727990724]},"meta":{"arrondissement":"PARIS 8E ARRDT","adresse":"JARDINS DES CHAMPS ELYSEES - JARDIN DES AMBASSADEURS / 10 AVENUE DES CHAMPS ELYSEES"}},{"taille":{"h":5,"p":48},"nom":"Laurier sauce","info":{"genre":"Laurus","espece":"nobilis","stade_developpement":"Adulte"},"id":"1a2be3d5bad976daf0dc125b3477cb9f597fb890","geo":{"type":"Point","coordinates":[2.339823366401752,48.82221457931862]},"meta":{"arrondissement":"PARIS 14E ARRDT","adresse":"PARC MONTSOURIS / 28 BOULEVARD JOURDAN"}},{"taille":{"h":2,"p":40},"nom":"Laurier sauce","info":{"genre":"Laurus","espece":"nobilis","stade_developpement":"Jeune (arbre)Adulte"},"id":"a98ce0ce93025ba7e8a4232db4c67ae8b025111f","geo":{"type":"Point","coordinates":[2.3432365415964282,48.82804708427607]},"meta":{"arrondissement":"PARIS 13E ARRDT","adresse":"CRECHE COLLECTIVE / 101 RUE DE LA GLACIERE"}},{"taille":{"h":5,"p":50},"nom":"Laurier sauce","info":{"genre":"Laurus","espece":"nobilis","stade_developpement":"Adulte"},"id":"00541cc28060e4d9a44591865fee495b6ffd3ae6","geo":{"type":"Point","coordinates":[2.391794584102648,48.86124743034406]},"meta":{"arrondissement":"PARIS 20E ARRDT","adresse":"CIMETIERE DU PERE LACHAISE / DIV 57"}},{"taille":{"h":8,"p":80},"nom":"Laurier sauce","info":{"genre":"Laurus","espece":"nobilis"},"id":"524ed48c08410bae51bc6be643a4f03783a74f00","geo":{"type":"Point","coordinates":[2.342284503128149,48.82451905732637]},"meta":{"arrondissement":"PARIS 13E ARRDT","adresse":"ECOLE MATERNELLE / 87 RUE BRILLAT SAVARIN"}},{"taille":{"h":2,"p":25},"nom":"Laurier sauce","info":{"genre":"Laurus","espece":"nobilis","stade_developpement":"Jeune (arbre)"},"id":"aa0190f0b788ed22a9f770cab02eee674c8ba8b7","geo":{"type":"Point","coordinates":[2.2914616757532142,48.86276082599883]},"meta":{"arrondissement":"PARIS 16E ARRDT","adresse":"JARDINS DU TROCADERO / 3 PLACE DE VARSOVIE"}},{"taille":{"h":2,"p":25},"nom":"Laurier sauce","info":{"genre":"Laurus","espece":"nobilis","stade_developpement":"Jeune (arbre)"},"id":"b9019025b9209d3b7f9df1f24d2fcd80eb476f4e","geo":{"type":"Point","coordinates":[2.291423295894449,48.86281857999557]},"meta":{"arrondissement":"PARIS 16E ARRDT","adresse":"JARDINS DU TROCADERO / 3 PLACE DE VARSOVIE"}},{"taille":{"h":0,"p":0},"nom":"Laurier sauce","info":{"genre":"Laurus","espece":"nobilis"},"id":"fff76dc53224450e78ed430c3fd6c75fb06c688f","geo":{"type":"Point","coordinates":[2.350406690950706,48.83447525624817]},"meta":{"arrondissement":"PARIS 13E ARRDT","adresse":"SQUARE RENE LE GALL / 1 RUE EMILE DESLANDRES"}},{"taille":{"h":5,"p":10},"nom":"Laurier sauce","info":{"genre":"Laurus","espece":"nobilis","stade_developpement":"Jeune (arbre)"},"id":"e7ee4ebae1c8052904790698e88b4241ba368425","geo":{"type":"Point","coordinates":[2.395465705463597,48.86192292972352]},"meta":{"arrondissement":"PARIS 20E ARRDT","adresse":"CIMETIERE DU PERE LACHAISE / DIV 44"}},{"taille":{"h":2,"p":10},"nom":"Laurier sauce","info":{"genre":"Laurus","espece":"nobilis"},"id":"845df3d54d6ec48c47346f573fea7297648e09fa","geo":{"type":"Point","coordinates":[2.404440424748493,48.90770021820196]},"meta":{"arrondissement":"SEINE-SAINT-DENIS","adresse":"CIMETIERE DE PANTIN / DIV 19"}},{"taille":{"h":5,"p":20},"nom":"Laurier sauce","info":{"genre":"Laurus","espece":"nobilis","stade_developpement":"Jeune (arbre)"},"id":"e468a0e71631e0f005d12e8c680da0aafd7c8119","geo":{"type":"Point","coordinates":[2.366360179422041,48.80947843281273]},"meta":{"arrondissement":"VAL-DE-MARNE","adresse":"CIMETIERE D''IVRY / DIV 27"}},{"taille":{"h":8,"p":50},"nom":"Laurier sauce","info":{"genre":"Laurus","espece":"nobilis","stade_developpement":"Adulte"},"id":"65345c4ef11af7934800bda0552e0682c7bfafa7","geo":{"type":"Point","coordinates":[2.444605612324346,48.83737703402922]},"meta":{"arrondissement":"BOIS DE VINCENNES","adresse":"PARC FLORAL DE PARIS / ROUTE DE LA PYRAMIDE"}},{"taille":{"h":4,"p":40},"nom":"Laurier sauce","info":{"genre":"Laurus","espece":"nobilis","stade_developpement":"Jeune (arbre)Adulte"},"id":"f4215559b9092b65fa4ed9b50c00b485ba43e734","geo":{"type":"Point","coordinates":[2.293383189769576,48.827467243752615]},"meta":{"arrondissement":"PARIS 15E ARRDT","adresse":"CENTRE SPORTIF DE LA PORTE DE LA PLAINE / 13 RUE DU GENERAL GUILLAUMAT"}},{"taille":{"h":1,"p":5},"nom":"Laurier sauce","info":{"genre":"Laurus","espece":"nobilis","stade_developpement":"Jeune (arbre)"},"id":"5d507d795a403a38095e16e1f9eb23b36a62d58b","geo":{"type":"Point","coordinates":[2.339315021730366,48.889209167166456]},"meta":{"arrondissement":"PARIS 18E ARRDT","adresse":"CIMETIERE ST VINCENT / AVENUE LATERALE N1 / DIV 9"}},{"taille":{"h":2,"p":25},"nom":"Laurier sauce","info":{"genre":"Laurus","espece":"nobilis","stade_developpement":"Jeune (arbre)"},"id":"5f9eed467d047becc7d2354feece4292375fed9a","geo":{"type":"Point","coordinates":[2.291361558487318,48.86268949017576]},"meta":{"arrondissement":"PARIS 16E ARRDT","adresse":"JARDINS DU TROCADERO / 3 PLACE DE VARSOVIE"}},{"taille":{"h":6,"p":70},"nom":"Laurier sauce","info":{"genre":"Laurus","espece":"nobilis","stade_developpement":"Jeune (arbre)Adulte"},"id":"e36599e695e23c741e87caa8b3790eeef059ea58","geo":{"type":"Point","coordinates":[2.292553438916002,48.88893140884065]},"meta":{"arrondissement":"PARIS 17E ARRDT","adresse":"CENTRE SPORTIF COURCELLES / 209 RUE DE COURCELLES"}},{"taille":{"h":4,"p":35},"nom":"Laurier sauce","info":{"genre":"Laurus","espece":"nobilis","stade_developpement":"Jeune (arbre)Adulte"},"id":"32a542eb3d139f4f6bbdda6accdfe0b9f9fff6fd","geo":{"type":"Point","coordinates":[2.371199387587223,48.811570558076404]},"meta":{"arrondissement":"VAL-DE-MARNE","adresse":"CIMETIERE D''IVRY / DIV 7"}},{"taille":{"h":3,"p":20},"nom":"Laurier","info":{"genre":"Laurus","espece":"n. sp."},"id":"317e18027a1b9c99963fc217ce5de4f00748dd5c","geo":{"type":"Point","coordinates":[2.392786490760803,48.87083105707972]},"meta":{"arrondissement":"PARIS 20E ARRDT","adresse":"JARDIN PARTAGE / 2 BIS CITE LEROY"}},{"taille":{"h":2,"p":10},"nom":"Laurier sauce","info":{"genre":"Laurus","espece":"nobilis","stade_developpement":"Jeune (arbre)"},"id":"086bed7b032c1548fe790ff9bd3b46c78cef41ec","geo":{"type":"Point","coordinates":[2.291255669053704,48.862819026359915]},"meta":{"arrondissement":"PARIS 16E ARRDT","adresse":"JARDINS DU TROCADERO / 3 PLACE DE VARSOVIE"}},{"taille":{"h":5,"p":70},"info":{"genre":"Laurus"},"id":"56a3081522a4f41102540d16fa1aeb132e218823","geo":{"type":"Point","coordinates":[2.369984747677301,48.85956502504338]},"meta":{"arrondissement":"PARIS 11E ARRDT","adresse":"PROMENADE DE L ALLEE VERTE / 1BIS ALLEE VERTE"}},{"taille":{"h":2,"p":20},"nom":"Laurier sauce","info":{"genre":"Laurus","espece":"nobilis","stade_developpement":"Jeune (arbre)"},"id":"5ef8ab6a9db8fea66fd55b7ae0cf484d3da3fa2b","geo":{"type":"Point","coordinates":[2.412369548237284,48.86753723356467]},"meta":{"arrondissement":"PARIS 20E ARRDT","adresse":"LE VAU (20) EM A"}}]