[{"taille":{"h":0,"p":0},"nom":"Nerprun","info":{"genre":"Rhamnus","espece":"cathartica"},"id":"de852bcdae806d6d068519bbc16afb57f4c6caea","geo":{"type":"Point","coordinates":[2.454703796961561,48.82038575083796]},"meta":{"arrondissement":"BOIS DE VINCENNES"}},{"taille":{"h":0,"p":0},"nom":"Nerprun","info":{"genre":"Rhamnus","espece":"cathartica"},"id":"4677a8e8a04656ef5669f10b79bc5d536ad55fb3","geo":{"type":"Point","coordinates":[2.458133298055329,48.82106298130249]},"meta":{"arrondissement":"BOIS DE VINCENNES"}},{"taille":{"h":3,"p":18},"info":{"genre":"Rhamnus","espece":"alaternus","stade_developpement":"Jeune (arbre)"},"id":"57f70ddb70bf630bd30f67b0ffa4e1f4b3c6227f","geo":{"type":"Point","coordinates":[2.2791159311899802,48.87244443587318]},"meta":{"arrondissement":"PARIS 16E ARRDT"}},{"taille":{"h":1,"p":10},"nom":"Nerprun","info":{"genre":"Rhamnus","espece":"alaternus","stade_developpement":"Jeune (arbre)","variete":"''Argenteovariegata''"},"id":"a2d9eb693d02e38de977293638de17224147bbf7","geo":{"type":"Point","coordinates":[2.338665726910673,48.8889769201979]},"meta":{"arrondissement":"PARIS 18E ARRDT"}},{"taille":{"h":1,"p":10},"nom":"Nerprun","info":{"genre":"Rhamnus","espece":"alaternus","stade_developpement":"Jeune (arbre)","variete":"''Argenteovariegata''"},"id":"08129864d1c8cd757ad297e204c5d0044fdb3885","geo":{"type":"Point","coordinates":[2.339051056986457,48.889136411853734]},"meta":{"arrondissement":"PARIS 18E ARRDT"}}]